simple_generation/__init__.py
simple_generation/cli.py
simple_generation/simple_generation.py
simple_generation/utils.py
simple_generation/vlm/__init__.py
simple_generation/vlm/utils.py
simple_generation/vlm/vlm.py
simple_generation-0.6.3.dist-info/LICENSE
simple_generation-0.6.3.dist-info/METADATA
simple_generation-0.6.3.dist-info/WHEEL
simple_generation-0.6.3.dist-info/entry_points.txt
simple_generation-0.6.3.dist-info/RECORD
