Metadata-Version: 2.1
Name: simple-generation
Version: 0.6.3
Summary: A python package to run inference with HuggingFace checkpoints wrapping many convenient features.
License: Apache Software License 2.0
Author: Giuseppe Attanasio
Author-email: giuseppeattanasio6@gmail.com
Requires-Python: >=3.9,<4.0
Classifier: License :: Other/Proprietary License
Classifier: Programming Language :: Python :: 3
Classifier: Programming Language :: Python :: 3.9
Classifier: Programming Language :: Python :: 3.10
Classifier: Programming Language :: Python :: 3.11
Classifier: Programming Language :: Python :: 3.12
Provides-Extra: all
Provides-Extra: vlm
Requires-Dist: accelerate (>=0.20.3)
Requires-Dist: bitsandbytes (>=0.39.1)
Requires-Dist: codecarbon (>=2.1.4)
Requires-Dist: datasets (>=2.12.0)
Requires-Dist: gradio (>=4.37.2,<5.0.0) ; extra == "all"
Requires-Dist: langcodes (>=3.4.0,<4.0.0) ; extra == "all"
Requires-Dist: optimum (>=1.9.0)
Requires-Dist: peft (>=0.3.0)
Requires-Dist: pillow (>=10.3.0) ; extra == "vlm" or extra == "all"
Requires-Dist: pyopenssl (>=23.2.0)
Requires-Dist: scipy (>=1.10.1)
Requires-Dist: tokenizers (>=0.13.3)
Requires-Dist: transformers (>=4.41.2,<5.0.0)
